fborm/__init__.py
fborm/__main__.py
fborm/commands.py
fborm/ext.py
fborm/objects.py
fborm/parse.py
fborm/patch.py
fborm/sample_config.py
fborm/types.py
fborm/util.py
fogbugz_orm-0.3.19.dist-info/DESCRIPTION.rst
fogbugz_orm-0.3.19.dist-info/METADATA
fogbugz_orm-0.3.19.dist-info/RECORD
fogbugz_orm-0.3.19.dist-info/WHEEL
fogbugz_orm-0.3.19.dist-info/metadata.json
fogbugz_orm-0.3.19.dist-info/top_level.txt
