Metadata-Version: 2.0
Name: fogbugz-orm
Version: 0.3.19
Summary: FogBugz API Object Relational Mapper (ORM)
Home-page: https://github.com/dougn/fogbugz-orm/
Author: Doug Napoleone
Author-email: doug.napoleone+fborm@gmail.com
License: BSD
Keywords: fogbugz,api,orm
Platform: UNKNOWN
Classifier: Development Status :: 4 - Beta
Classifier: Environment :: Web Environment
Classifier: Programming Language :: Python
Classifier: Programming Language :: Python :: 2.6
Classifier: Programming Language :: Python :: 2.7
Classifier: Intended Audience :: Developers
Classifier: Intended Audience :: System Administrators
Classifier: License :: OSI Approved :: BSD License
Classifier: Topic :: Internet :: WWW/HTTP
Classifier: Topic :: Software Development :: Libraries :: Python Modules
Requires-Dist: fogbugz
Requires-Dist: jsontree
